assetWorksheet.py
asset_worksheet-0.0.1.dist-info/LICENSE
asset_worksheet-0.0.1.dist-info/METADATA
asset_worksheet-0.0.1.dist-info/WHEEL
asset_worksheet-0.0.1.dist-info/entry_points.txt
asset_worksheet-0.0.1.dist-info/top_level.txt
asset_worksheet-0.0.1.dist-info/RECORD
