Metadata-Version: 2.1
Name: asset-worksheet
Version: 0.0.1
Summary: Generates an automated inventory worksheets from GCP Asset Inventory APIs. Current Supported: FedRAMP Attachment 13
Author-email: Jamie Duncan <jamieduncan@google.com>
License: Apache License
Project-URL: Homepage, https://github.com/jduncan-rva/GCPAttachment13
Project-URL: Bug Tracker, https://github.com/jduncan-rva/GCPAttachment13/issues
Classifier: Programming Language :: Python :: 3
Classifier: License :: OSI Approved :: Apache Software License
Classifier: Operating System :: OS Independent
Requires-Python: >=3.7
License-File: LICENSE
Requires-Dist: google-cloud-asset
Requires-Dist: google-cloud-storage
